CHANGELOG.txt
LICENCE.txt
MANIFEST.in
README.txt
setup.py
metaunit/__init__.py
metaunit.egg-info/PKG-INFO
metaunit.egg-info/SOURCES.txt
metaunit.egg-info/dependency_links.txt
metaunit.egg-info/top_level.txt