Metadata-Version: 1.1
Name: metaunit
Version: 0.0.3
Summary: Metaunit is python package for unit conversion.
Home-page: UNKNOWN
Author: Bathiya Seneviratne
Author-email: seneviratne.bathiya@gmail.com
License: MIT
Platform: UNKNOWN
Classifier: Development Status :: 5 - Production/Stable
Classifier: Intended Audience :: Education
Classifier: Operating System :: OS Independent
Classifier: License :: OSI Approved :: MIT License
Classifier: Programming Language :: Python :: 3
